README.txt
setup.py
cs/__init__.py
cs.recipe.checkinterval.egg-info/PKG-INFO
cs.recipe.checkinterval.egg-info/SOURCES.txt
cs.recipe.checkinterval.egg-info/dependency_links.txt
cs.recipe.checkinterval.egg-info/entry_points.txt
cs.recipe.checkinterval.egg-info/namespace_packages.txt
cs.recipe.checkinterval.egg-info/not-zip-safe
cs.recipe.checkinterval.egg-info/requires.txt
cs.recipe.checkinterval.egg-info/top_level.txt
cs/recipe/__init__.py
cs/recipe/checkinterval/__init__.py
docs/HISTORY.txt
docs/INSTALL.txt
docs/LICENSE.GPL
docs/LICENSE.txt