Metadata-Version: 1.1
Name: cs.recipe.checkinterval
Version: 1.0
Summary: Buildout recipe that calculates the python-check-interval value for your zope instance
Home-page: http://github.com/codesyntax/cs.recipe.checkinterval
Author: Mikel Larreategi
Author-email: mlarreategi@codesyntax.com
License: GPL
Keywords: python zope interpreter check interval
Platform: UNKNOWN
Classifier: Framework :: Buildout :: Recipe
Classifier: Framework :: Zope2
Classifier: Programming Language :: Python
